LICENSE
README.rst
setup.py
mplpub/__init__.py
mplpub/mplpub.py
mplpub.egg-info/PKG-INFO
mplpub.egg-info/SOURCES.txt
mplpub.egg-info/dependency_links.txt
mplpub.egg-info/requires.txt
mplpub.egg-info/top_level.txt
mplpub/templates/acs
mplpub/templates/acs_dcol
mplpub/templates/base
mplpub/templates/base_2.0_update
mplpub/templates/jpcl_toc
mplpub/templates/natcom
mplpub/templates/natcom_dcol
mplpub/templates/phd
mplpub/templates/phd_fw
mplpub/templates/rsc
mplpub/templates/rsc_dcol